README.md
setup.cfg
setup.py
hebireki/__init__.py
hebireki/era.py
hebireki/wareki.py
hebireki.egg-info/PKG-INFO
hebireki.egg-info/SOURCES.txt
hebireki.egg-info/dependency_links.txt
hebireki.egg-info/top_level.txt